pyciactions/IWorkflow.py
pyciactions/__init__.py
pyciactions/generate.py
pyciactions/github/__init__.py
pyciactions/github/job.py
pyciactions/github/on.py
pyciactions/github/workflow.py
pyciactions-1.0.12.dist-info/LICENSE
pyciactions-1.0.12.dist-info/METADATA
pyciactions-1.0.12.dist-info/WHEEL
pyciactions-1.0.12.dist-info/top_level.txt
pyciactions-1.0.12.dist-info/RECORD
