Metadata-Version: 2.1
Name: pyciactions
Version: 1.0.12
Summary: Declarative builder for Github Action Scripts
Home-page: https://github.com/JBongars/pyciactions
Author: Julien Bongars
License-File: LICENSE
Requires-Dist: dataclasses (==0.6)
Requires-Dist: PyYAML (==6.0)
